{
  "$schema": "https://mintlify.com/docs.json",
  "name": "GLAM CLI",
  "theme": "aspen",
  "colors": {
    "primary": "#8B5CF6",
    "light": "#A78BFA",
    "dark": "#6D28D9"
  },
  "navbar": {
    "primary": {
      "type": "github",
      "href": "https://github.com/glamsystems/glam-cli"
    }
  },
  "footer": {
    "socials": {
      "github": "https://github.com/glamsystems/glam-cli"
    }
  },
  "navigation": {
    "tabs": [
      {
        "tab": "Documentation",
        "groups": [
          {
            "group": "Get Started",
            "pages": [
              "introduction",
              "installation",
              "quickstart",
              "configuration"
            ]
          },
          {
            "group": "Core Concepts",
            "pages": [
              "concepts/vaults",
              "concepts/delegates",
              "concepts/integrations"
            ]
          },
          {
            "group": "Guides",
            "pages": [
              "guides/creating-vaults",
              "guides/managing-assets",
              "guides/delegate-permissions",
              "guides/investor-operations"
            ]
          }
        ]
      },
      {
        "tab": "Command Reference",
        "groups": [
          {
            "group": "Vault Management",
            "pages": [
              "commands/vault",
              "commands/env",
              "commands/transfer"
            ]
          },
          {
            "group": "Trading & Swaps",
            "pages": [
              "commands/jupiter"
            ]
          },
          {
            "group": "DeFi Integrations",
            "pages": [
              "commands/drift-protocol",
              "commands/drift-vaults",
              "commands/kamino-lend",
              "commands/kamino-vaults",
              "commands/kamino-farms",
              "commands/marinade",
              "commands/lst",
              "commands/stake"
            ]
          },
          {
            "group": "Access Control",
            "pages": [
              "commands/delegate",
              "commands/integration"
            ]
          },
          {
            "group": "Investor Operations",
            "pages": [
              "commands/invest",
              "commands/manage"
            ]
          },
          {
            "group": "Advanced",
            "pages": [
              "commands/alt",
              "commands/timelock",
              "commands/cctp"
            ]
          }
        ]
      }
    ]
  }
}
